Metadata-Version: 2.1
Name: webclrs
Version: 0.0.1
Summary: A nicer color palette for the web in Python. (https://clrs.cc/).
Home-page: https://github.com/suzil/webclrs
License: MIT
Platform: UNKNOWN
Classifier: License :: OSI Approved :: MIT License
Classifier: Programming Language :: Python
Classifier: Programming Language :: Python :: 3
Classifier: Programming Language :: Python :: 3.6
Classifier: Programming Language :: Python :: Implementation :: CPython
Classifier: Programming Language :: Python :: Implementation :: PyPy
Requires-Python: >=3.6.0
